smartscoutscrape/__init__.py
smartscoutscrape/amazon.py
smartscoutscrape/cli.py
smartscoutscrape/pandas.py
smartscoutscrape/smartscout.py
smartscoutscrape/sqlite.py
smartscoutscrape/utils.py
smartscoutscrape-0.2.1.dist-info/entry_points.txt
smartscoutscrape-0.2.1.dist-info/LICENSE.txt
smartscoutscrape-0.2.1.dist-info/METADATA
smartscoutscrape-0.2.1.dist-info/WHEEL
smartscoutscrape-0.2.1.dist-info/RECORD
