Metadata-Version: 2.1
Name: smartscoutscrape
Version: 0.2.1
Summary: Lightweight data-extraction & general use library for smartscout.com
Home-page: https://github.com/regulad/smartscout-scrape
License: Apache-2.0
Keywords: scraper,data science,requests,python,data
Author: Parker Wahle
Author-email: regulad@regulad.xyz
Maintainer: Parker Wahle
Maintainer-email: regulad@regulad.xyz
Requires-Python: >=3.11,<4.0
Classifier: Development Status :: 3 - Alpha
Classifier: Environment :: Console
Classifier: Intended Audience :: Developers
Classifier: License :: OSI Approved :: Apache Software License
Classifier: Natural Language :: English
Classifier: Operating System :: OS Independent
Classifier: Programming Language :: Python :: 3
Classifier: Programming Language :: Python :: 3.11
Classifier: Programming Language :: Python :: 3 :: Only
Classifier: Topic :: Software Development :: Libraries :: Python Modules
Provides-Extra: all
Requires-Dist: beautifulsoup4 (>=4.12.2,<5.0.0)
Requires-Dist: jupyter (>=1.0.0,<2.0.0)
Requires-Dist: minify-html (>=0.11.1,<0.12.0)
Requires-Dist: pandas (>=2,<3)
Requires-Dist: requests (>=2.31.0,<3.0.0)
Requires-Dist: rich (>=13.4.2,<14.0.0)
Requires-Dist: selenium (>=4.10.0,<5.0.0)
Requires-Dist: tqdm (>=4,<5)
Requires-Dist: typer[all] (>=0.9.0,<0.10.0)
Requires-Dist: undetected-chromedriver (>=3.5.0,<4.0.0)
Project-URL: CI, https://github.com/regulad/smartscout-scrape/actions
Project-URL: Documentation, https://smartscout-scrape.readthedocs.io
Project-URL: Download, https://pypi.org/project/smartscoutscrape/
Project-URL: Issues, https://github.com/regulad/smartscout-scrape/issues
Project-URL: Repository, https://github.com/regulad/smartscout-scrape
